mlmp/__init__.py
mlmp/mouse.dll
mlmp/normal_mouse_data.py
mlmp/predict.py
mlmp/time_seq_mouse_data.py
mlmp/time_seq_train.py
mlmp/train.py
mlmp-0.1.3.dist-info/METADATA
mlmp-0.1.3.dist-info/WHEEL
mlmp-0.1.3.dist-info/top_level.txt
mlmp-0.1.3.dist-info/RECORD
