Metadata-Version: 2.4
Name: mlmp
Version: 0.1.3
Summary: A Python package for mouse path control and training.
Home-page: https://github.com/zaixia108/MLMousePath
Author: zaixia108
Author-email: zaixia108 <xvbowen2012@gmail.com>
Project-URL: homepage, https://github.com/zaixia108/MLMousePath
Classifier: Programming Language :: Python :: 3
Classifier: License :: OSI Approved :: MIT License
Classifier: Operating System :: OS Independent
Requires-Python: >=3.8
Requires-Dist: onnxruntime
Dynamic: author
Dynamic: home-page
Dynamic: requires-python
